torchliter/__init__.py
torchliter/exception.py
torchliter/stub.py
torchliter/utils.py
torchliter/writer.py
torchliter/engine/__init__.py
torchliter/engine/_types.py
torchliter/engine/auto.py
torchliter/engine/base.py
torchliter/engine/buffers.py
torchliter/engine/events.py
torchliter/engine/utils.py
torchliter/factory/__init__.py
torchliter/factory/registry.py
torchliter/factory/utils.py
torchliter-0.3.4.dist-info/LICENSE
torchliter-0.3.4.dist-info/METADATA
torchliter-0.3.4.dist-info/WHEEL
torchliter-0.3.4.dist-info/top_level.txt
torchliter-0.3.4.dist-info/RECORD
