Metadata-Version: 2.1
Name: torchliter
Version: 0.3.4
Summary: A lightweight training tool for pytorch projects.
Home-page: UNKNOWN
Author: Chenchao Zhao
Author-email: chenchao.zhao@gmail.com
License: MIT
Platform: UNKNOWN
License-File: LICENSE
Requires-Dist: torch
Requires-Dist: numpy
Requires-Dist: dataclasses
